pylibretro/__init__.py
pylibretro/core.py
pylibretro/libretro.h
pylibretro/utils.py
pylibretro-0.4.1.dist-info/LICENSE.md
pylibretro-0.4.1.dist-info/METADATA
pylibretro-0.4.1.dist-info/WHEEL
pylibretro-0.4.1.dist-info/top_level.txt
pylibretro-0.4.1.dist-info/RECORD
