Metadata-Version: 2.2
Name: pylibretro
Version: 0.4.1
Summary: WIP Python library that runs Libretro cores
Author: James Ravindran
License: GPL-3.0-or-later
Project-URL: Repository, https://github.com/jamesravi/pylibretro
Keywords: libretro,emulator,retroarch
Classifier: Development Status :: 2 - Pre-Alpha
Classifier: Operating System :: POSIX :: Linux
Classifier: Operating System :: Microsoft :: Windows
Classifier: Topic :: Software Development :: Libraries :: Python Modules
Classifier: License :: OSI Approved :: GNU General Public License v3 or later (GPLv3+)
Classifier: Programming Language :: Python
Classifier: Programming Language :: Python :: 3
Requires-Python: >=3.10
License-File: LICENSE.md
Requires-Dist: cffi
Requires-Dist: pycparser-fake-libc
Requires-Dist: numpy
Provides-Extra: examples
Requires-Dist: imageio; extra == "examples"
Requires-Dist: tqdm; extra == "examples"
Requires-Dist: pillow; extra == "examples"
Requires-Dist: opencv-python; extra == "examples"
